drpy/__init__.py
drpy/plotting.py
drpy/utils.py
drpy/validate.py
drpy/batch/__init__.py
drpy/batch/core.py
drpy/image/__init__.py
drpy/image/core.py
drpy/image/utils.py
drpy/modeling/__init__.py
drpy/modeling/core.py
drpy/modeling/function.py
drpy/onedspec/__init__.py
drpy/onedspec/center.py
drpy/onedspec/core.py
drpy/onedspec/io.py
drpy/twodspec/__init__.py
drpy/twodspec/longslit.py
drpy/twodspec/utils.py
drpy-0.0.1.0.dist-info/LICENSE
drpy-0.0.1.0.dist-info/METADATA
drpy-0.0.1.0.dist-info/WHEEL
drpy-0.0.1.0.dist-info/top_level.txt
drpy-0.0.1.0.dist-info/RECORD
